iqm/station_control/client/__init__.py
iqm/station_control/client/authentication.py
iqm/station_control/client/list_models.py
iqm/station_control/client/py.typed
iqm/station_control/client/qon.py
iqm/station_control/client/station_control.py
iqm/station_control/client/utils.py
iqm/station_control/client/iqm_server/error.py
iqm/station_control/client/iqm_server/grpc_utils.py
iqm/station_control/client/iqm_server/iqm_server_client.py
iqm/station_control/client/serializers/__init__.py
iqm/station_control/client/serializers/channel_property_serializer.py
iqm/station_control/client/serializers/datetime_serializers.py
iqm/station_control/client/serializers/playlist_serializers.py
iqm/station_control/client/serializers/run_serializers.py
iqm/station_control/client/serializers/setting_node_serializer.py
iqm/station_control/client/serializers/struct_serializer.py
iqm/station_control/client/serializers/sweep_serializers.py
iqm/station_control/client/serializers/task_serializers.py
iqm/station_control/interface/__init__.py
iqm/station_control/interface/list_with_meta.py
iqm/station_control/interface/py.typed
iqm/station_control/interface/pydantic_base.py
iqm/station_control/interface/station_control.py
iqm/station_control/interface/models/__init__.py
iqm/station_control/interface/models/circuit.py
iqm/station_control/interface/models/dut.py
iqm/station_control/interface/models/dynamic_quantum_architecture.py
iqm/station_control/interface/models/jobs.py
iqm/station_control/interface/models/monitor.py
iqm/station_control/interface/models/observation.py
iqm/station_control/interface/models/observation_set.py
iqm/station_control/interface/models/run.py
iqm/station_control/interface/models/sequence.py
iqm/station_control/interface/models/static_quantum_architecture.py
iqm/station_control/interface/models/sweep.py
iqm/station_control/interface/models/type_aliases.py
iqm_station_control_client-12.0.3.dist-info/LICENSE.txt
iqm_station_control_client-12.0.3.dist-info/METADATA
iqm_station_control_client-12.0.3.dist-info/WHEEL
iqm_station_control_client-12.0.3.dist-info/top_level.txt
iqm_station_control_client-12.0.3.dist-info/RECORD
