Metadata-Version: 2.1
Name: iqm-station-control-client
Version: 12.0.3
Summary: Python client for communicating with Station Control Service
Author-email: IQM Finland Oy <info@meetiqm.com>
License: Apache License
Project-URL: Documentation, https://docs.meetiqm.com/iqm-station-control-client/
Project-URL: Homepage, https://pypi.org/project/iqm-station-control-client/
Classifier: Development Status :: 4 - Beta
Classifier: Programming Language :: Python :: 3 :: Only
Classifier: Topic :: Scientific/Engineering :: Physics
Classifier: Intended Audience :: Science/Research
Requires-Python: >=3.11
License-File: LICENSE.txt
Requires-Dist: iqm-data-definitions <3.0,>=2.18
Requires-Dist: opentelemetry-exporter-otlp <2.0,>=1.25.0
Requires-Dist: protobuf <5.0,>=4.25.3
Requires-Dist: types-protobuf
Requires-Dist: grpcio <2.0,>=1.65.4
Requires-Dist: pydantic <3.0,>=2.10.4
Requires-Dist: PyYAML <7.0,>=6.0
Requires-Dist: requests ==2.32.3
Requires-Dist: types-requests
Requires-Dist: tqdm >=4.59.0
Requires-Dist: types-tqdm
Requires-Dist: iqm-exa-common <28,>=27.4.3
